atlas_mpl_style/__init__.py
atlas_mpl_style/_utils.py
atlas_mpl_style/plot.py
atlas_mpl_style/stats.py
atlas_mpl_style/uhi.py
atlas_mpl_style/utils.py
atlas_mpl_style/stylesheets/atlas.mplstyle
atlas_mpl_style/stylesheets/paper.mplstyle
atlas_mpl_style/stylesheets/print.mplstyle
atlas_mpl_style/stylesheets/slides.mplstyle
atlas_mpl_style/testing/ampl-test.tex
atlas_mpl_style-0.25.0.dist-info/licenses/LICENSE.md
atlas_mpl_style-0.25.0.dist-info/WHEEL
atlas_mpl_style-0.25.0.dist-info/METADATA
atlas_mpl_style-0.25.0.dist-info/RECORD
