Metadata-Version: 2.4
Name: atlas-mpl-style
Version: 0.25.0
Summary: ATLAS style for Matplotlib 3.0+
Keywords: plotting,atlas,matplotlib,cern,root,hep,high-energy-physics,physics
Author-email: Beojan Stanislaus <beojan.stanislaus@cern.ch>
Requires-Python: >=3.9
Classifier: Development Status :: 5 - Production/Stable
Classifier: Intended Audience :: Science/Research
Classifier: Topic :: Scientific/Engineering :: Visualization
Classifier: License :: OSI Approved :: GNU General Public License v3 or later (GPLv3+)
Classifier: Programming Language :: Python :: 3
Classifier: Programming Language :: Python :: 3.9
Classifier: Programming Language :: Python :: 3.10
Classifier: Programming Language :: Python :: 3.11
Classifier: Programming Language :: Python :: 3.12
Classifier: Programming Language :: Python :: 3.13
License-File: LICENSE.md
Requires-Dist: matplotlib>=3.8
Requires-Dist: numpy
Requires-Dist: numexpr
Requires-Dist: pandas
Requires-Dist: importlib-resources>=6
Requires-Dist: packaging
Project-URL: Documentation, https://atlas-mpl.readthedocs.io/en/latest/
Project-URL: Home, https://github.com/beojan/atlas-mpl
